vistan/__init__.py
vistan/hyperparams.py
vistan/inference.py
vistan/interface.py
vistan/objectives.py
vistan/scratchpad.py
vistan/test.py
vistan/utilities.py
vistan/vi_families.py
vistan/vi_on_stan.py
vistan/recipes/__init__.py
vistan/recipes/advi.py
vistan/recipes/flows.py
vistan/recipes/fullrank.py
vistan/recipes/meanfield.py
vistan/recipes/method0.py
vistan/recipes/method1.py
vistan/recipes/method2.py
vistan/recipes/method3a.py
vistan/recipes/method3b.py
vistan/recipes/method4a.py
vistan/recipes/method4b.py
vistan/recipes/method4c.py
vistan/recipes/method4d.py
vistan-0.0.0.6.dist-info/LICENSE
vistan-0.0.0.6.dist-info/METADATA
vistan-0.0.0.6.dist-info/WHEEL
vistan-0.0.0.6.dist-info/top_level.txt
vistan-0.0.0.6.dist-info/RECORD
