Metadata-Version: 2.1
Name: vistan
Version: 0.0.0.6
Summary: Library to run VI algorithms on Stan models.
Home-page: https://github.com/abhiagwl/vistan
Author: Abhinav Agrawal
Author-email: aagrawal@umass.edu
License: GNU General Public License v3.0
Platform: UNKNOWN
Requires-Dist: scipy
Requires-Dist: pystan
Requires-Dist: autograd
Requires-Dist: joblib
Requires-Dist: tqdm
